ftx/__init__.py
ftx/api.py
ftx-1.2.0.dist-info/LICENSE
ftx-1.2.0.dist-info/METADATA
ftx-1.2.0.dist-info/WHEEL
ftx-1.2.0.dist-info/top_level.txt
ftx-1.2.0.dist-info/RECORD
