Metadata-Version: 2.1
Name: ftx
Version: 1.2.0
Summary: Unofficial python3 FTX exchange API 1.2.0
Home-page: https://github.com/quan-digital/ftx/tree/v1.2
Author: thomgabriel
Author-email: thomgabriel@protonmail.com
License: MIT
Download-URL: https://github.com/quan-digital/ftx/archive/v1.1.tar.gz
Keywords: ftx,bitcoin,crypto-api,api-connector,exchange-api,crypto-exchange,digital-currency,trading
Platform: UNKNOWN
Classifier: Development Status :: 5 - Production/Stable
Classifier: Intended Audience :: Developers
Classifier: Intended Audience :: Financial and Insurance Industry
Classifier: Topic :: Software Development
Classifier: License :: OSI Approved :: MIT License
Classifier: Programming Language :: Python :: 3
Classifier: Programming Language :: Python :: 3.4
Classifier: Programming Language :: Python :: 3.5
Classifier: Programming Language :: Python :: 3.6
Classifier: Programming Language :: Python :: 3.7
Classifier: Programming Language :: Python :: 3.8
Classifier: Operating System :: OS Independent
License-File: LICENSE
